peakdetect/__init__.py
peakdetect/peakdetect.py
peakdetect-1.2.dist-info/METADATA
peakdetect-1.2.dist-info/WHEEL
peakdetect-1.2.dist-info/top_level.txt
peakdetect-1.2.dist-info/RECORD
