Metadata-Version: 2.1
Name: peakdetect
Version: 1.2
Summary: Simple peak detection
Home-page: https://github.com/avhn/peakdetect
Author: avhn
Author-email: UNKNOWN
License: UNKNOWN
Platform: UNKNOWN
Requires-Dist: numpy
Requires-Dist: scipy
